{
  "swagger": "2.0",
  "info": {
    "title": "Rafting API",
    "description": "Water Rafting Web Services",
    "version": "1.0.0"
  },
  "host": "water-rafting.onrender.com",
  "basePath": "/",
  "schemes": ["https"],
  "paths": {
    "/": {
      "get": {
        "description": "",
        "responses": {
          "200": {
            "description": "OK"
          }
        }
      }
    },
    "/trips/": {
      "get": {
        "description": "",
        "responses": {
          "200": {
            "description": "OK"
          }
        }
      }
    },
    "/trips/create": {
      "post": {
        "description": "",
        "responses": {
          "default": {
            "description": ""
          }
        }
      }
    },
    "/trips/{id}": {
      "get": {
        "description": "",
        "parameters": [
          {
            "name": "id",
            "in": "path",
            "required": true,
            "type": "string"
          }
        ],
        "responses": {
          "default": {
            "description": ""
          }
        }
      }
    },
    "/trips/add": {
      "post": {
        "description": "",
        "responses": {
          "400": {
            "description": "Bad Request"
          }
        }
      }
    },
    "/trips/edit/{id}": {
      "put": {
        "description": "",
        "parameters": [
          {
            "name": "id",
            "in": "path",
            "required": true,
            "type": "string"
          }
        ],
        "responses": {
          "400": {
            "description": "Bad Request"
          }
        }
      }
    },
    "/trips/delete/{id}": {
      "delete": {
        "description": "",
        "parameters": [
          {
            "name": "id",
            "in": "path",
            "required": true,
            "type": "string"
          }
        ],
        "responses": {
          "default": {
            "description": ""
          }
        }
      }
    }
  }
}